Workbook

Sheet 1. Мой процесс
A1: «ЭКОНОМИКА ИИ» — Шаблон расчёта
A2: Синим цветом — ячейки для ввода · Чёрным — расчёты · Жёлтый фон — обязательно заполнить
A4: ШАГ 1 — ВЫБЕРИТЕ ВАШУ СФЕРУ
A5: Ваша сфера деятельности | B5: Банковская автоматизация | D5: Выберите из списка: HR / Медицина / Маркетинг / Логистика / Ритейл / Другое
A6: IT Банка. Сопровожденние Пользователей АБС "ЦФТ-Банк"
A7: ШАГ 2 — ОПИШИТЕ ПРОЦЕСС, КОТОРЫЙ ХОТИТЕ АВТОМАТИЗИРОВАТЬ
A8: Название процесса | B8: Разработка АРМа «Адаптация под DBI» для перехода АБС «ЦФТ-Банк» с Платформы 1 на 2MCA DBI | D8: HR: скрининг резюме | Медицина: обработка карточек пациентов | Логистика: планирование маршрутов | Маркетинг: подготовка отчётов | Ответы на заявки пользователей в JIRA
A9: Что происходит сейчас (вход → выход) | B9: На входе локальный код функционала на PL+ На выходе откорректированный под требования DBI | D9: Опишите одной строкой: что поступает на вход и что получается на выходе
A10: Где хранятся данные сейчас | B10: В БД Oracle. Выгружаются с помощью CFT Platform IDE в виде каталогов с текстовыми файлами с кодом функционала, экранных форм и т.п. | D10: Например: 1С / CRM / Excel / бумажные документы / несколько систем сразу / Outlook/JIRA
A11: Данные оцифрованы? (да / частично / нет) | B11: Да | D11: Если «нет» или «частично» — в бюджете нужна статья на подготовку данных
A13: ШАГ 3 — ЛЮДИ И ВРЕМЯ (основа для расчёта FTE)
A14: Сколько человек выполняют этот процесс | B14: 4 | D14: Укажите количество сотрудников, занятых в процессе
A15: Сколько часов в день тратит ОДИН человек | B15: 2 | D15: Только время на этот конкретный процесс, не всю смену
A16: Рабочих дней в месяце | B16: 22 | D16: Обычно 22 рабочих дня в месяц
A17: Средний оклад сотрудника (₽/мес, «на руки») | B17: 350000 | D17: Сумма, которую получает сотрудник. Налоги и накладные добавим автоматически
A18: Доля времени, которую займёт ИИ (%) | B18: 0.7 | D18: Реалистично: 70–90%. Сложные случаи останутся людям.
A20: АВТОРАСЧЁТ — сколько времени занимает процесс
A21: Часов в месяц на весь процесс | B21: =B14*B15*B16 -> 176 | D21: кол-во людей × часов/день × рабочих дней
A22: Высвобождаемые FTE (эквивалент полных ставок) | B22: =B14*B15*B16*B18/(8*B16) -> 0.7 | D22: Сколько полных ставок (FTE) мы реально высвобождаем с учётом того, что сотрудники заняты процессом не полный день
A23: Реальная стоимость одного FTE (с налогами и накладными) | B23: =B17*1.3*1.4 -> 637000 | D23: Оклад × 1.30 (налоги) × 1.40 (накладные расходы)
A24: 💰 ПРЯМАЯ ЭКОНОМИЯ В МЕСЯЦ (Hard Benefits) | B24: =B22*B23 -> 445900 | D24: Эта цифра перейдёт автоматически на лист «3. Эффект»
A26: ➡ Перейдите на лист «2. Бюджет» и заполните статьи расходов

Sheet 2. Бюджет (TCO)
A1: 💰 БЮДЖЕТ ИИ-ПРОЕКТА — Total Cost of Ownership (TCO)
A2: Синим — вводите свои цифры. Если статья не применима — оставьте 0.
A4: CAPEX — единовременные затраты на старте (платите один раз)
A5: Разработка / настройка ИИ-системы | B5: 420000 | C5: Оплата разработчику или вендору за создание системы
A6: Интеграция с вашими системами (1С, CRM…) | B6: 210000 | C6: Подключение ИИ к существующим программам. Заложите 50–100% от стоимости разработки
A7: Подготовка и очистка данных | B7: 20000 | C7: ..
A8: Разметка данных (если нужно) | B8: 0 | C8: Ручная разметка примеров для обучения модели. Стоимость: кол-во объектов × цена за объект
A9: Обучение сотрудников | B9: 20000 | C9: Тренинги, инструкции, адаптационный период
A10: Прочие единовременные расходы | B10: 20000 | C10: Например: юридическая экспертиза договора, лицензии на ПО
A11: ИТОГО CapEx | B11: =SUM(B5:B10) -> 690000 | C11: ← Это ваши стартовые инвестиции (IC в формуле NPV)
A13: OPEX — ежемесячные расходы на работу системы
A14: Подписка на облачный сервис / платформу | B14: 4790 | C14: Например: Nodul, Make, YandexGPT API, GigaChat API
A15: Токены API (оплата за запросы) | B15: 0 | C15: Кол-во запросов/мес × средний размер запроса × цена токена
A16: Зарплата сотрудника поддержки (доля) | B16: 110000 | C16: Часть ставки человека, который следит за системой
A17: Переобучение модели (в пересчёте на мес) | B17: 110000 | C17: Если переобучаете раз в квартал — разделите стоимость на 3
A18: Прочие операционные расходы | B18: 20000 | C18: Мониторинг, аудит безопасности, резерв на ошибки ИИ
A19: ИТОГО OpEx в месяц | B19: =SUM(B14:B18) -> 244790
A21: ИТОГОВЫЙ TCO — полная стоимость владения
A22: TCO за первый год | B22: =B11+B19*12 -> 3627480 | C22: CapEx + OpEx × 12 месяцев
A23: TCO за второй год | B23: =B19 -> 244790 | C23: Только OpEx — CapEx уже не повторяется
A24: TCO за три года | B24: =B22+B23*2 -> 4117060 | C24: Год 1 + Год 2 + Год 3
A26: ⚠️ СВЕТОФОР: доля скрытых расходов в CapEx
A27: Скрытые расходы (данные + разметка + интеграция) | B27: =IF(B11=0, 0, (B6+B7+B8)/B11) -> 0.33333333 | C27: =IF(B11=0, "введите CapEx", IF((B6+B7+B8)/B11<0.3, "🟢 Хорошо — скрытые расходы под контролем", IF((B6+B7+B8)/B11<0.5, "🟡 Внимание — скрытые расходы значительны", "🔴 Стоп — скрытые расходы превышают 50% CapEx"))) -> 🟡 Внимание — скрытые расходы значительны
A29: ➡ Перейдите на лист «3. Эффект» для расчёта ROI и окупаемости

Sheet 3. Эффект и окупаемость
A1: 📈 ЭФФЕКТ И ОКУПАЕМОСТЬ — ROI · Точка безубыточности · NPV
A2: Данные из листов 1 и 2 подтягиваются автоматически. Вам нужно заполнить только Soft Benefits.
A4: HARD BENEFITS — прямая экономия (считается автоматически)
A5: Высвобождённые FTE | B5: ='1. Мой процесс'!B22 -> 0.7 | C5: Из листа 1 — автоматически
A6: Реальная стоимость 1 FTE | B6: ='1. Мой процесс'!B23 -> 637000 | C6: Оклад с налогами и накладными
A7: 💰 Прямая экономия в месяц | B7: ='1. Мой процесс'!B24 -> 445900 | C7: FTE × стоимость FTE
A8: Прямая экономия в год | B8: =B7*12 -> 5350800 | C8: × 12 месяцев
A10: SOFT BENEFITS — скрытая прибыль (оцените сами)
A11: Рост выручки за счёт ИИ (%) | B11: 0.05 | C11: HR: быстрее нанимаем → раньше закрываем вакансии → меньше потерь | Медицина: больше пациентов за то же время | Логистика: меньше опозданий → меньше штрафов
A12: Текущая выручка / оборот в месяц (₽) | B12: 5000000 | C12: Выручка вашего подразделения или компании в месяц
A13: Снижение потерь от ошибок (%) | B13: 0.02 | C13: Ошибки ручного ввода, неверные решения, просроченные задачи
A14: Стоимость ошибок сейчас (₽/мес) | B14: 100000 | C14: Штрафы, переделки, компенсации, упущенные сделки
A15: 💰 Скрытая прибыль в месяц (итого) | B15: =B12*B11+B14*B13 -> 252000 | C15: Рост выручки + снижение потерь
A16: Скрытая прибыль в год | B16: =B15*12 -> 3024000 | C16: × 12 месяцев
A18: ИТОГОВЫЙ ЭФФЕКТ
A19: Совокупный эффект в месяц | B19: =B7+B15 -> 697900 | C19: Hard + Soft Benefits
A20: Совокупный эффект в год | B20: =B19*12 -> 8374800 | C20: × 12 месяцев
A21: OpEx в месяц (из бюджета) | B21: ='2. Бюджет (TCO)'!B19 -> 244790 | C21: Ежемесячные расходы на систему — из листа 2
A22: Чистый эффект в месяц | B22: =B19-B21 -> 453110 | C22: Эффект минус расходы на поддержку
A24: КЛЮЧЕВЫЕ МЕТРИКИ ПРОЕКТА
A25: ROI первого года (%) | B25: =IF('2. Бюджет (TCO)'!B22=0, 0, (B20-'2. Бюджет (TCO)'!B22)/'2. Бюджет (TCO)'!B22) -> 1.3087102 | C25: =IF('2. Бюджет (TCO)'!B22=0, "", IF((B20-'2. Бюджет (TCO)'!B22)/'2. Бюджет (TCO)'!B22>1, "🟢 Отличный результат (>100%)", IF((B20-'2. Бюджет (TCO)'!B22)/'2. Бюджет (TCO)'!B22>0, "🟡 Положительный ROI", "🔴 Проект убыточен — пересмотрите параметры"))) -> 🟢 Отличный результат (>100%)
A26: Точка безубыточности (месяцев) | B26: =IF(B22<=0, "нет окупаемости", ROUND('2. Бюджет (TCO)'!B11/B22, 1)) -> 1.5 | C26: =IF(B22<=0, "🔴 Проект не окупается", IF('2. Бюджет (TCO)'!B11/B22<=9, "🟢 Отлично — до 9 месяцев", IF('2. Бюджет (TCO)'!B11/B22<=18, "🟡 Хорошо — 9–18 месяцев", "🔴 Риск — более 18 месяцев"))) -> 🟢 Отлично — до 9 месяцев
A28: NPV — чистая приведённая стоимость за 3 года
A29: Ставка дисконтирования (r) | B29: 0.12 | C29: Обычно: ключевая ставка + 2–3%. В 2026 году — около 12–15%
A30: Чистый эффект Год 1 (в сегод. ₽) | B30: =B22*12/(1+B29)^1 -> 4854750 | C30: Год 1 дисконтируем на (1+r)¹
A31: Чистый эффект Год 2 (в сегод. ₽) | B31: =B22*12*1.1/(1+B29)^2 -> 4768058 | C31: Год 2: +10% (модель дообучилась)
A32: Чистый эффект Год 3 (в сегод. ₽) | B32: =B22*12*1.1/(1+B29)^3 -> 4257194.7 | C32: Год 3: стабильный уровень
A33: ✅ NPV проекта за 3 года | B33: =B30+B31+B32-'2. Бюджет (TCO)'!B11 -> 13190003 | C33: =IF(B30+B31+B32-'2. Бюджет (TCO)'!B11>0, "🟢 NPV положительный — проект выгоден", "🔴 NPV отрицательный — проект убыточен даже с учётом будущих доходов") -> 🟢 NPV положительный — проект выгоден
A35: ➡ Перейдите на лист «4. Стресс-тест» — что будет, если что-то пойдёт не так?

Sheet 4. Стресс-тест
A1: ⚠️ СТРЕСС-ТЕСТ — Что будет, если что-то пойдёт не так?
A2: Измените коэффициенты (синие ячейки) и посмотрите, как меняется экономика проекта
A4: БАЗОВЫЕ ПОКАЗАТЕЛИ (из ваших расчётов)
A5: CapEx (стартовые инвестиции) | B5: ='2. Бюджет (TCO)'!B11 -> 690000 | C5: ← из ваших расчётов
A6: OpEx в месяц (базовый) | B6: ='2. Бюджет (TCO)'!B19 -> 244790 | C6: ← из ваших расчётов
A7: Эффект в месяц (базовый) | B7: ='3. Эффект и окупаемость'!B19 -> 697900 | C7: ← из ваших расчётов
A8: Точка безубыточности (базовая) | B8: ='3. Эффект и окупаемость'!B26 -> 1.5 | C8: ← из ваших расчётов
A9: ROI первого года (базовый) | B9: ='3. Эффект и окупаемость'!B25 -> 1.3087102 | C9: ← из ваших расчётов
A11: СЦЕНАРИИ — измените коэффициенты и пересчитайте
A12: Коэффициент удорожания / снижения | B12: Значение | C12: Что означает
A13: Интеграция обошлась в X раз дороже плана | B13: 2 | C13: 2.0 = в два раза дороже, 3.0 = в три раза дороже
A14: Model Drift: эффект снизился до X% от плана | B14: 0.7 | C14: 0.7 = эффект упал до 70%. 1.0 = без изменений
A15: Токены стоят в X раз дороже прогноза | B15: 1.5 | C15: 1.5 = в полтора раза дороже. Влияет на OpEx
A16: Задержка запуска (добавить месяцев к CapEx) | B16: 2 | C16: Дополнительные месяцы, пока система не работает
A18: ПЕРЕСЧЁТ С УЧЁТОМ СТРЕСС-СЦЕНАРИЯ
A19: CapEx в стресс-сценарии | B19: ='2. Бюджет (TCO)'!B5+'2. Бюджет (TCO)'!B7+'2. Бюджет (TCO)'!B8+'2. Бюджет (TCO)'!B9+'2. Бюджет (TCO)'!B10+'2. Бюджет (TCO)'!B6*B13 -> 900000 | C19: Интеграция × ваш коэффициент удорожания
A20: OpEx в стресс-сценарии (мес) | B20: ='2. Бюджет (TCO)'!B14*B15+'2. Бюджет (TCO)'!B15+'2. Бюджет (TCO)'!B16+'2. Бюджет (TCO)'!B17+'2. Бюджет (TCO)'!B18 -> 247185 | C20: Токены × коэффициент удорожания + остальные статьи
A21: Эффект в стресс-сценарии (мес) | B21: =B7*B14 -> 488530 | C21: Базовый эффект × коэффициент снижения (Model Drift)
A22: Чистый эффект в стресс-сценарии (мес) | B22: =B21-B20 -> 241345
A24: 🔴 Точка безубыточности (стресс) | B24: =IF(B22<=0, "не окупается", ROUND((B19+'2. Бюджет (TCO)'!B19*B16)/B22, 1)) -> 5.8 | C24: =IF(B22<=0, "🔴 Проект не окупается в этом сценарии", IF((B19+'2. Бюджет (TCO)'!B19*B16)/B22<=18, "🟡 Окупается, но позже", "🔴 Более 18 месяцев — высокий риск")) -> 🟡 Окупается, но позже
A25: 🔴 ROI первого года (стресс) | B25: =IF(B19=0, 0, (B21*12-(B19+'2. Бюджет (TCO)'!B19*B16+B20*12))/(B19+'2. Бюджет (TCO)'!B19*B16+B20*12)) -> 0.34587447
A27: 💬 ВОПРОС ДЛЯ ОБСУЖДЕНИЯ В ГРУППЕ:
A28: При каком сочетании коэффициентов (интеграция × N, эффект × M) ваш проект перестаёт окупаться за 18 месяцев? Запишите ответ ниже и будьте готовы объяснить это руководителю.
A29: Ваш ответ:
A31: ✅ Готово! Ваш расчёт завершён. Теперь подготовьте питч на 3 минуты: Проблема → Решение → Цифры
